swehockey/__init__.py
swehockey/swehockey_scraper.py
swehockey_scraper-1.5.dist-info/METADATA
swehockey_scraper-1.5.dist-info/WHEEL
swehockey_scraper-1.5.dist-info/top_level.txt
swehockey_scraper-1.5.dist-info/RECORD
