Metadata-Version: 2.1
Name: swehockey_scraper
Version: 1.5
Summary: Functions to scrape ice hockey data and statistics from swehockey
Home-page: https://github.com/msjoelin/swehockey_scraper
Download-URL: https://pypi.org/project/swehockey_scraper/
Author: Marcus Sjölin
Author-email: marcussjolin89@gmail.com
License: MIT
Keywords: ice hockey,scraping,sport analytics,shl,analys,ishockey,hockeyallsvenskan
Requires-Dist: numpy
Requires-Dist: pandas
Requires-Dist: bs4
Requires-Dist: datetime
Requires-Dist: requests
